<?xml version="1.0" encoding="UTF-8"?>
<mappings xmlns="http://dozer.sourceforge.net"
      xmlns:xsi="http://www.w3.org/2001/XMLSchema-instance"
      xsi:schemaLocation="http://dozer.sourceforge.net http://dozer.sourceforge.net/schema/beanmapping.xsd">
    
    <mapping>
  		<class-a>org.gestoresmadrid.core.general.model.vo.UsuarioVO</class-a>
  		<class-b>org.gestoresmadrid.oegamComun.acceso.model.bean.DetalleUsuarioBean</class-b>
  		<field custom-converter-id="dozerBigDecimalToStringConverter">  
  			<a>estadoUsuario</a>
  			<b>estadoUsuario</b>	
  		</field>
  	</mapping>
  	<mapping>
  		<class-a>org.gestoresmadrid.core.general.model.vo.FuncionVO</class-a>
  		<class-b>org.gestoresmadrid.oegamComun.acceso.model.bean.MenuFuncionBean</class-b>
  		<field>  
  			<a>aplicacion.descAplicacion</a>
  			<b>descAplicacion</b>	
  		</field>
  		<field>  
  			<a>id.codigoFuncion</a>
  			<b>codigoFuncion</b>	
  		</field>
  		<field>  
  			<a>id.codigoAplicacion</a>
  			<b>codigoAplicacion</b>	
  		</field>
  		<field>
  			<a>codFuncionPadre</a>
  			<b>codigoFuncionPadre</b>
  		</field>
  	</mapping>
  	<mapping>
  		<class-a>utilidades.web.Menu</class-a>
  		<class-b>org.gestoresmadrid.oegamComun.acceso.model.bean.MenuFuncionBean</class-b>
  		<field>  
  			<a>desc_funcion</a>
  			<b>descFuncion</b>	
  		</field>
  		<field>  
  			<a>codigo_funcion</a>
  			<b>codigoFuncion</b>	
  		</field>
  		<field>  
  			<a>codigo_aplicacion</a>
  			<b>codigoAplicacion</b>	
  		</field>
  		<field>
  			<a>codigo_funcion_padre</a>
  			<b>codigoFuncionPadre</b>
  		</field>
  		<field>
  			<a>url</a>
  			<b>url</b>
  		</field>
  		<field>
  			<a>nivel</a>
  			<b>nivel</b>
  		</field>
  		<field>
  			<a>orden</a>
  			<b>orden</b>
  		</field>
  		<field>
  			<a>tipo</a>
  			<b>tipo</b>
  		</field>
  	</mapping>

  	<mapping>
  		<class-a>org.gestoresmadrid.core.estacionITV.model.vo.EstacionITVVO</class-a>
  		<class-b>trafico.beans.EstacionITVBean</class-b>
  		<field>  
  			<a>id</a>
  			<b>estacionITV</b>	
  		</field>
  	</mapping>
  	<mapping>
  		<class-a>org.gestoresmadrid.core.general.model.vo.FuncionVO</class-a>
  		<class-b>utilidades.web.Menu</class-b>
  		<field>  
  			<a>id.codigoAplicacion</a>
  			<b>codigo_aplicacion</b>	
  		</field>
  		  <field>  
  			<a>id.codigoFuncion</a>
  			<b>codigo_funcion</b>	
  		</field>
  		<field>  
  			<a>descFuncion</a>
  			<b>desc_funcion</b>	
  		</field>
  		<field>
  			<a>codFuncionPadre</a>
  			<b>codigo_funcion_padre</b>
  		</field>
  		<field>  
  			<a>url</a>
  			<b>url</b>	
  		</field>
  		<field>
  			<a>nivel</a>
  			<b>nivel</b>	
  		</field>
  		<field>  
  			<a>orden</a>
  			<b>orden</b>	
  		</field>
  		<field>  
  			<a>tipo</a>
  			<b>tipo</b>	
  		</field>
  	</mapping>
  	
  	<mapping>
  		<class-a>org.gestoresmadrid.core.general.model.vo.UsuarioVO</class-a>
  		<class-b>utilidades.web.Usuario</class-b>
  		<field>  
  			<a>nif</a>
  			<b>nif</b>	
  		</field>
  		<field>
  			<a>idUsuario</a>
  			<b>id_usuario</b>	
  		</field>
  		<field>  
  			<a>numColegiado</a>
  			<b>num_colegiado</b>	
  		</field>
  		<field>  
  			<a>numColegiadoNacional</a>
  			<b>num_colegiado_nacional</b>	
  		</field>
  		<field>  
  			<a>estadoUsuario</a>
  			<b>estado_usuario</b>	
  		</field>
  		<field>  
  			<a>apellidosNombre</a>
  			<b>apellidos_nombre</b>	
  		</field>
  		<field>  
  			<a>correoElectronico</a>
  			<b>correo_electronico</b>	
  		</field>
  		<field>  
  			<a>ultimaConexion</a>
  			<b>ultima_conexion</b>	
  		</field>
  		<field>  
  			<a>fechaRenovacion</a>
  			<b>fecha_renovacion</b>	
  		</field>
  	</mapping>
  	
  	<mapping>
  		<class-a>org.gestoresmadrid.oegamComun.accesos.view.dto.AplicacionDto</class-a>
  		<class-b>utilidades.web.Aplicacion</class-b>
  		<field>  
  			<a>codigoAplicacion</a>
  			<b>codigo_aplicacion</b>	
  		</field>
  		<field>  
  			<a>descAplicacion</a>
  			<b>desc_aplicacion</b>	
  		</field>
  	</mapping>
  	
  	<mapping>
  		<class-a>org.gestoresmadrid.core.general.model.vo.FuncionVO</class-a>
  		<class-b>org.gestoresmadrid.oegamComun.acceso.model.bean.PermisoUsuarioBean</class-b>
  		<field>  
  			<a>id.codigoFuncion</a>
  			<b>codigoFuncion</b>	
  		</field>
  	</mapping>
  	<mapping>
  		<class-a>org.gestoresmadrid.core.general.model.vo.NotificacionVO</class-a>
  		<class-b>org.gestoresmadrid.oegam2comun.view.dto.NotificacionDto</class-b>
  		<field>
  			<a>tipoTramite.tipoTramite</a>
  			<b>tipoTramite</b>
  		</field>
  	</mapping>
  	<mapping map-null="false">
  		<class-a>org.gestoresmadrid.oegam2comun.trafico.view.dto.TramiteTrafMatrDto</class-a>
		<class-b>org.gestoresmadrid.core.trafico.model.vo.TramiteTrafMatrVO</class-b>
		<field custom-converter-id="dozerSINOConverter">
  			<a>entregaFactMatriculacion</a>
  			<b>entregaFactMatriculacion</b>
  		</field>
  		<field custom-converter-id="dozerSINOConverter">
  			<a>exento576</a>
  			<b>exento576</b>
  		</field>
  		<field custom-converter-id="dozerSINOConverter">
  			<a>reduccion576</a>
  			<b>reduccion576</b>
  		</field>
  		<field custom-converter-id="dozerSNConverter">
  			<a>justificadoIvtm</a>
  			<b>justificadoIvtm</b>
  		</field>
  		<field>
			<a>ivtmMatriculacionDto</a>
			<b>ivtmMatriculacionVO</b>
		</field>
		<field>
			<a>deducir576</a>
			<b>aDeducir576</b>
		</field>
		<field>
			<a>numDeclaracionComp576</a>
			<b>nDeclaracionComp576</b>
		</field>
		<field custom-converter-id="dozerSNConverter">
  			<a>carsharing</a>
  			<b>carsharing</b>
  		</field>
  		<field custom-converter-id="dozerSNConverter">
  			<a>checkJustifFicheroIvtm</a>
  			<b>checkJustifFicheroIvtm</b>
  		</field>
  	</mapping>
  	<mapping type="bi-directional">
  		<class-a>org.gestoresmadrid.core.ivtmMatriculacion.model.vo.IvtmMatriculacionVO</class-a>
  		<class-b>org.gestoresmadrid.oegam2comun.ivtmMatriculacion.model.view.dto.IvtmMatriculacionDto</class-b>
  		<field custom-converter-id="dozerFechaConverter">
			<a>fechaRequerida</a>
			<b>fechaReq</b>
		</field>
  	</mapping>
  	<mapping>
		<class-a>org.gestoresmadrid.oegamComun.persona.view.dto.PersonaDto</class-a>
		<class-b>org.gestoresmadrid.core.personas.model.vo.PersonaVO</class-b>
		<field custom-converter-id="dozerSNConverter">
  			<a>indefinido</a>
  			<b>indefinido</b>
  		</field>
		<field>
			<a>fechaCadCarnetCond</a>
			<b>fechaCaducidadCarnet</b>
		</field>
		<field>
			<a>fechaCaducidadNif</a>
			<b>fechaCaducidadNIF</b>
		</field>
		<field>
			<a>nif</a>
			<b>id.nif</b>
		</field>
		<field>
			<a>numColegiado</a>
			<b>id.numColegiado</b>
		</field>
	</mapping>

  	<mapping>
  		<class-a>org.gestoresmadrid.oegamComun.vehiculo.view.dto.VehiculoDto</class-a>
  		<class-b>org.gestoresmadrid.core.vehiculo.model.vo.VehiculoVO</class-b>
  		<field custom-converter-id="dozerSNConverter">
  			<a>importado</a>
  			<b>importado</b>
  		</field>
  		<field custom-converter-id="dozerSINOConverter">
  			<a>subastado</a>
  			<b>subastado</b>
  		</field>
  		<field custom-converter-id="dozerSINOConverter">
  			<a>vehiculoAgricola</a>
  			<b>vehiculoAgricola</b>
  		</field>
  		<field custom-converter-id="dozerSINOConverter">
  			<a>vehiculoTransporte</a>
  			<b>vehiculoTransporte</b>
  		</field>
  		<field custom-converter-id="dozerSINOConverter">
  			<a>vehiUsado</a>
  			<b>vehiUsado</b>
  		</field>
  		<field custom-converter-id="dozerSNConverter">
  			<a>diplomatico</a>
  			<b>diplomatico</b>
  		</field>
  		<field custom-converter-id="dozerSNConverter">
  			<a>excesoPeso</a>
  			<b>excesoPeso</b>
  		</field>
  		<field>
			<a>cdModVeh</a>
			<b>cdmodveh</b>
		</field>
		<field custom-converter-id="dozerSINOConverter">
			<a>checkFechaCaducidadITV</a>
			<b>checkFechaCaducidadItv</b>
		</field>
		<field>
			<a>direccion</a>
			<b>direccion</b>
		</field>
		<field>
			<a>codItv</a>
			<b>coditv</b>
		</field>
		<field>
			<a>codItvOriginal</a>
			<b>coditvOriginal</b>
		</field>
		<field>
			<a>fecDesde</a>
			<b>fecdesde</b>
		</field>
		<field>
			<a>fichaTecnicaRD750</a>
			<b>fichaTecnicaRd750</b>
		</field>
		<field>
			<a>carburante</a>
			<b>idCarburante</b>
		</field>
		<field>
			<a>color</a>
			<b>idColor</b>
		</field>
		<field>
			<a>criterioConstruccion</a>
			<b>idCriterioConstruccion</b>
		</field>
		<field>
			<a>criterioUtilizacion</a>
			<b>idCriterioUtilizacion</b>
		</field>
		<field>
			<a>epigrafe</a>
			<b>idEpigrafe</b>
		</field>
		<field>
			<a>lugarAdquisicion</a>
			<b>idLugarAdquisicion</b>
		</field>
		<field>
			<a>lugarPrimeraMatriculacion</a>
			<b>idLugarMatriculacion</b>
		</field>
		<field>
			<a>motivoItv</a>
			<b>idMotivoItv</b>
		</field>
		<field>
			<a>servicioTrafico.idServicio</a>
			<b>idServicio</b>
		</field>
		<field>
			<a>servicioTraficoAnterior.idServicio</a>
			<b>idServicioAnterior</b>
		</field>
		<field>
			<a>tipoTarjetaITV</a>
			<b>idTipoTarjetaItv</b>
		</field>
		<field>
			<a>nifIntegrador</a>
			<b>persona</b>
		</field>
		<field>
			<a>nifIntegrador.nif</a>
			<b>nifIntegrador</b>
		</field>
		<field>
			<a>tipVehi</a>
			<b>tipvehi</b>
		</field>
		<field>
			<a>numSerie</a>
			<b>nSerie</b>
		</field>
		<field>
			<a>numHomologacion</a>
			<b>nHomologacion</b>
		</field>
		<field>
			<a>numHomologacionBase</a>
			<b>nHomologacionBase</b>
		</field>
		<field>
			<a>numPlazasPie</a>
			<b>nPlazasPie</b>
		</field>
		<field>
			<a>numRuedas</a>
			<b>nRuedas</b>
		</field>
  	</mapping>
  	
  	<mapping>
  		<class-a>org.gestoresmadrid.oegam2comun.trafico.view.dto.TramiteTrafBajaDto</class-a>
  		<class-b>org.gestoresmadrid.core.trafico.model.vo.TramiteTrafBajaVO</class-b>
  		<field>
			<a>cartaDGTVehiculoMasDiezAn</a>
			<b>cartaDGTVehiculoMasDiezAnios</b>
		</field>
		<field>
			<a>certificadoMedioAmbiental</a>
			<b>certificadoMedioambiental</b>
		</field>	
  		<field custom-converter-id="dozerSINOConverter">
  			<a>bajaImpMunicipal</a>
  			<b>bajaImpMunicipal</b>
  		</field>
  		<field custom-converter-id="dozerSINOConverter">
  			<a>declaracionResiduo</a>
  			<b>declaracionResiduo</b>
  		</field>
  		<field custom-converter-id="dozerSINOConverter">
  			<a>imprPermisoCircu</a>
  			<b>imprPermisoCircu</b>
  		</field>
  		<field custom-converter-id="dozerSINOConverter">
  			<a>justificanteDenuncia</a>
  			<b>justificanteDenuncia</b>
  		</field>
  		<field custom-converter-id="dozerSINOConverter">
  			<a>pagoImpMunicipal</a>
  			<b>pagoImpMunicipal</b>
  		</field>
  		<field custom-converter-id="dozerSINOConverter">
  			<a>permisoCircu</a>
  			<b>permisoCircu</b>
  		</field>
  		<field custom-converter-id="dozerSINOConverter">
  			<a>declaracionJuradaExtravio</a>
  			<b>declaracionJuradaExtravio</b>
  		</field>
  		<field custom-converter-id="dozerSINOConverter">
  			<a>propiedadDesguace</a>
  			<b>propiedadDesguace</b>
  		</field>
  		<field custom-converter-id="dozerSINOConverter">
  			<a>tarjetaInspeccion</a>
  			<b>tarjetaInspeccion</b>
  		</field>
  		<field>
			<a>resCheckBtv</a>
			<b>resCheckBtv</b>
		</field>	
		<field custom-converter-id="dozerSINOConverter">
  			<a>autoInformeBtv</a>
  			<b>autoInformeBtv</b>
  		</field>
  		<field>
  			<a>idContrato</a>
  			<b>contrato.idContrato</b>
  		</field>
  	</mapping>
  	
  	<mapping>
  		<class-a>org.gestoresmadrid.oegam2comun.trafico.view.dto.TramiteTrafDto</class-a>
  		<class-b>org.gestoresmadrid.core.trafico.model.vo.TramiteTraficoVO</class-b>
		<field>
			<a>ybpdfDto</a>
			<b>ybpdf</b>
		</field>
 		<field>
			<a>vehiculoDto</a>
			<b>vehiculo</b>
		</field>
		<field>
			<a>idContrato</a>
			<b>contrato.idContrato</b>
		</field>
		<field>
			<a>usuarioDto</a>
			<b>usuario</b>
		</field>
		<field>
			<a>jefaturaTraficoDto</a>
			<b>jefaturaTrafico</b>
		</field>
		<field>
			<a>tasa</a>
			<b>tasa</b>
		</field>
		<field custom-converter-id="dozerSINOConverter">
  			<a>renting</a>
  			<b>renting</b>
  		</field>
  		<field custom-converter-id="dozerSINOConverter">
  			<a>exentoCem</a>
  			<b>exentoCem</b>
  		</field>
  		<field custom-converter-id="dozerSINOConverter">
  			<a>cambioDomicilio</a>
  			<b>cambioDomicilio</b>
  		</field>
  		<field>
			<a>regIedtm</a>
			<b>nRegIedtm</b>
		</field>
	</mapping>
	
	<mapping>
  		<class-a>org.gestoresmadrid.oegamComun.trafico.view.dto.TramiteTraficoDto</class-a>
  		<class-b>org.gestoresmadrid.core.trafico.model.vo.TramiteTraficoVO</class-b>
 		<field>
			<a>vehiculoDto</a>
			<b>vehiculo</b>
		</field>
		<field>
			<a>idContrato</a>
			<b>contrato.idContrato</b>
		</field>
		<field>
			<a>usuarioDto</a>
			<b>usuario</b>
		</field>
		<field>
			<a>jefaturaTraficoDto</a>
			<b>jefaturaTrafico</b>
		</field>
		<field>
			<a>tasa</a>
			<b>tasa</b>
		</field>
		<field custom-converter-id="dozerSINOConverter">
  			<a>renting</a>
  			<b>renting</b>
  		</field>
  		<field custom-converter-id="dozerSINOConverter">
  			<a>exentoCem</a>
  			<b>exentoCem</b>
  		</field>
  		<field custom-converter-id="dozerSINOConverter">
  			<a>cambioDomicilio</a>
  			<b>cambioDomicilio</b>
  		</field>
  		<field>
			<a>regIedtm</a>
			<b>nRegIedtm</b>
		</field>
	</mapping>
	
	<mapping>
		<class-a>org.gestoresmadrid.oegamComun.contrato.view.dto.ContratoDto</class-a>
		<class-b>org.gestoresmadrid.core.contrato.model.vo.ContratoVO</class-b>
		<field>
			<a>colegioDto</a>
			<b>colegio</b>
		</field>
		<field>
			<a>colegiadoDto</a>
			<b>colegiado</b>
		</field>
		<field>
			<a>jefaturaTraficoDto</a>
			<b>jefaturaTrafico</b>
		</field>
		<field>
			<a>aplicacionesDto</a>
			<b>aplicaciones</b>
		</field>
		<field>
			<a>mobileGest</a>
			<b>mobileG</b>
		</field>
	</mapping>
	
	<mapping>
		<class-a>org.gestoresmadrid.core.general.model.vo.ContratoUsuarioVO</class-a>
		<class-b>utilidades.web.Contrato</class-b>
		<field>
			<a>contrato.idContrato</a>
			<b>_id_contrato</b>
		</field>
		<field>
			<a>contrato.razonSocial</a>
			<b> _razon_social</b>
		</field>
		<field>
			<a>contrato.cif</a>
			<b> _cif</b>
		</field>
		<field>
			<a>contrato.via</a>
			<b>via</b>
		</field>
		<field>
			<a>contrato.municipio.nombre</a>
			<b>nombre</b>
		</field>
		<field>
			<a>contrato.provincia.nombre</a>
			<b>_nombre_provincia</b>
		</field>
	</mapping>
	
	<mapping>
		<class-a>org.gestoresmadrid.core.contrato.model.vo.ContratoVO</class-a>
		<class-b>utilidades.web.Contrato</class-b>
		<field>
			<a>colegiado.numColegiado</a>
			<b>_num_colegiado</b>
		</field>
		<field>
			<a>anagramaContrato</a>
			<b> _anagrama</b>
		</field>
		<field>
			<a>cif</a>
			<b> _cif</b>
		</field>
		<field>
			<a>idContrato</a>
			<b>_id_contrato</b>
		</field>
		<field>
			<a>razonSocial</a>
			<b>_razon_social</b>
		</field>
		<field>
			<a>provincia.nombre</a>
			<b>_nombre_provincia</b>
		</field>
		<field>
			<a>colegio.colegio</a>
			<b>_colegio</b>
		</field>
		<field>
			<a>jefaturaTrafico.jefaturaProvincial</a>
			<b>jefatura_Provincial</b>
		</field>
		<field>
			<a>correoElectronico</a>
			<b>correo_Electronico</b>
		</field>
		<field>
			<a>idTipoVia</a>
			<b>id_Tipo_Via</b>
		</field>
		<field>
			<a>via</a>
			<b>nombre_Via</b>
		</field>
		<field>
			<a>razonSocial</a>
			<b>nombre</b>
		</field>
		<field>
			<a>codPostal</a>
			<b>cod_postal</b>
		</field>
		<field>
			<a>idProvincia</a>
			<b>id_provincia</b>
		</field>
		<field>
			<a>idMunicipio</a>
			<b>id_municipio</b>
		</field>
		<field>
			<a>via</a>
			<b>via</b>
		</field>
	</mapping>
	
	
	<mapping>
		<class-a>org.gestoresmadrid.oegamComun.colegiado.view.dto.ColegiadoDto</class-a>
		<class-b>org.gestoresmadrid.core.general.model.vo.ColegiadoVO</class-b>
		<field>
			<a>usuario.idUsuario</a>
			<b>idUsuario</b>
		</field>
		<field>
			<a>usuario</a>
			<b>usuario</b>
		</field>
	</mapping>
	
<!-- 	<mapping>
		<class-a>hibernate.entities.general.Colegiado</class-a>
		<class-b>org.gestoresmadrid.core.general.model.vo.ColegiadoVO</class-b>
	</mapping> -->

	<mapping map-null="false">
		<class-a>org.gestoresmadrid.oegamComun.direccion.view.dto.DireccionDto</class-a>
		<class-b>org.gestoresmadrid.core.direccion.model.vo.DireccionVO</class-b>
		<field>
			<a>idTipoVia</a>
			<b>idTipoVia</b>
		</field>
	</mapping>
	
	<mapping>
		<class-a>org.gestoresmadrid.oegam2comun.personas.view.dto.EvolucionPersonaDto</class-a>
		<class-b>org.gestoresmadrid.core.personas.model.vo.EvolucionPersonaVO</class-b>
		<field>
			<a>numColegiado</a>
			<b>id.numColegiado</b>
		</field>
		<field>
			<a>nif</a>
			<b>id.nif</b>
		</field>
		<field>
			<a>fechaHora</a>
			<b>id.fechaHora</b>
		</field>
	</mapping>
	
	<mapping>
		<class-a>org.gestoresmadrid.oegam2comun.tasas.view.dto.EvolucionTasaDto</class-a>
		<class-b>org.gestoresmadrid.core.tasas.model.vo.EvolucionTasaVO</class-b>
		<field>
			<a>codigoTasa</a>
			<b>id.codigoTasa</b>
		</field>
		<field>
			<a>fechaHora</a>
			<b>id.fechaHora</b>
		</field>
		<field>
			<a>tasa</a>
			<b>tasa</b>
		</field>
		<field>
			<a>usuario</a>
			<b>usuario</b>
		</field>
	</mapping>
<!-- 	<mapping>
		<class-a>org.gestoresmadrid.oegam2comun.evolucionTasa.view.dto.EvolucionTasaDto</class-a>
		<class-b>org.gestoresmadrid.core.tasas.model.vo.EvolucionTasaVO</class-b>
		<field>
			<a>fechaHora</a>
			<b>id.fechaHora</b>
		</field>
	</mapping> -->
	
	<mapping>
		<class-a>org.gestoresmadrid.oegam2comun.trafico.view.dto.EvolucionTramiteTraficoDto</class-a>
		<class-b>org.gestoresmadrid.core.trafico.model.vo.EvolucionTramiteTraficoVO</class-b>
		<field>
			<a>estadoAnterior</a>
			<b>id.estadoAnterior</b>
		</field>
		<field>
			<a>estadoNuevo</a>
			<b>id.estadoNuevo</b>
		</field>
		<field>
			<a>fechaCambio</a>
			<b>id.fechaCambio</b>
		</field>
		<field>
			<a>usuarioDto</a>
			<b>usuario</b>
		</field>
		<field>
			<a>numExpediente</a>
			<b>id.numExpediente</b>
		</field>
	</mapping>
	
	<mapping>
		<class-a>org.gestoresmadrid.oegam2comun.registradores.view.dto.TramiteRegistroDto</class-a>
		<class-b>org.gestoresmadrid.core.registradores.model.vo.TramiteRegistroVO</class-b>
		<field>
			<a>sociedad.nif</a>
			<b>cif</b>
		</field>
	</mapping>
	
	<mapping>
		<class-a>org.gestoresmadrid.oegam2comun.registradores.view.dto.EvolucionTramiteRegistroDto</class-a>
		<class-b>org.gestoresmadrid.core.registradores.model.vo.EvolucionTramiteRegistroVO</class-b>
		<field>
			<a>estadoAnterior</a>
			<b>id.estadoAnterior</b>
		</field>
		<field>
			<a>estadoNuevo</a>
			<b>id.estadoNuevo</b>
		</field>
		<field>
			<a>fechaCambio</a>
			<b>id.fechaCambio</b>
		</field>
		<field>
			<a>idTramiteRegistro</a>
			<b>id.idTramiteRegistro</b>
		</field>
	</mapping>
	
	<mapping>
		<class-a>org.gestoresmadrid.oegamComun.accesos.view.dto.FuncionDto</class-a>
		<class-b>org.gestoresmadrid.core.general.model.vo.FuncionVO</class-b>
		<field>
			<a>codigoAplicacion</a>
			<b>id.codigoAplicacion</b>
		</field>
		<field>
			<a>codigoFuncion</a>
			<b>id.codigoFuncion</b>
		</field>
		<field>
			<a>aplicacionDto</a>
			<b>aplicacion</b>
		</field>
	</mapping>
	
	<mapping>
		<class-a>org.gestoresmadrid.oegamComun.interviniente.view.dto.IntervinienteTraficoDto</class-a>
		<class-b>org.gestoresmadrid.core.intervinienteTrafico.model.vo.IntervinienteTraficoVO</class-b>
		<field>
			<a>codigoIAE</a>
			<b>codigoIae</b>
		</field>
		<field>
			<a>nifInterviniente</a>
			<b>id.nif</b>
		</field>
		<field>
			<a>numColegiado</a>
			<b>id.numColegiado</b>
		</field>
		<field>
			<a>numExpediente</a>
			<b>id.numExpediente</b>
		</field>
		<field>
			<a>tipoInterviniente</a>
			<b>id.tipoInterviniente</b>
		</field>
		<field custom-converter-id="dozerSINOConverter">
  			<a>autonomo</a>
  			<b>autonomo</b>
  		</field>
  		<field custom-converter-id="dozerSINOConverter">
  			<a>cambioDomicilio</a>
  			<b>cambioDomicilio</b>
  		</field>
	</mapping>
	
	<mapping>
		<class-a>org.gestoresmadrid.oegamComun.trafico.view.dto.JefaturaTraficoDto</class-a>
		<class-b>org.gestoresmadrid.core.trafico.model.vo.JefaturaTraficoVO</class-b>
		<field>
			<a>provinciaDto</a>
			<b>provincia</b>
		</field>
	</mapping>
	
	<mapping>
		<class-a>org.gestoresmadrid.oegamComun.vehiculo.view.dto.ServicioTraficoDto</class-a>
		<class-b>org.gestoresmadrid.core.vehiculo.model.vo.ServicioTraficoVO</class-b>
		<field>
			<a>tipoTramiteDto.tipoTramite</a>
			<b>tipoTramite</b>
		</field>
	</mapping>
	
	<mapping>
		<class-a>org.gestoresmadrid.oegamComun.direccion.view.dto.MunicipioDto</class-a>
		<class-b>org.gestoresmadrid.core.direccion.model.vo.MunicipioVO</class-b>
		<field>
			<a>idMunicipio</a>
			<b>id.idMunicipio</b>
		</field>
		<field>
			<a>idProvincia</a>
			<b>id.idProvincia</b>
		</field>
	</mapping>
	
	<mapping>
		<class-a>org.gestoresmadrid.oegamComun.persona.view.dto.PersonaDireccionDto</class-a>
		<class-b>org.gestoresmadrid.core.personas.model.vo.PersonaDireccionVO</class-b>
		<field>
			<a>numColegiado</a>
			<b>id.numColegiado</b>
		</field>
		<field>
			<a>nif</a>
			<b>id.nif</b>
		</field>
	</mapping>
	
	<mapping>
		<class-a>org.gestoresmadrid.oegam2comun.direccion.view.dto.ViaDto</class-a>
		<class-b>org.gestoresmadrid.core.direccion.model.vo.ViaVO</class-b>
		<field>
			<a>idProvincia</a>
			<b>provincia.idProvincia</b>
		</field>
		<field>
			<a>tipoViaIne</a>
			<b>tipoViaIne.idTipoVia</b>
		</field>
	</mapping>
	
	<mapping>
		<class-a>org.gestoresmadrid.oegam2comun.view.dto.YbpdfDto</class-a>
		<class-b>org.gestoresmadrid.core.ybpdf.model.vo.YbpdfVO</class-b>
		<field>
			<a>fechaEnvio</a>
			<b>fecha</b>
		</field>
	</mapping>
	
	<mapping>
		<class-a>org.gestoresmadrid.oegamComun.trafico.view.dto.TramiteTrafFacturacionDto</class-a>
		<class-b>org.gestoresmadrid.core.trafico.model.vo.TramiteTrafFacturacionVO</class-b>
		<field>
			<a>numExpediente</a>
			<b>id.numExpediente</b>
		</field>
		<field>
			<a>codTasa</a>
			<b>id.codigoTasa</b>
		</field>
		<field>
			<a>tipoTramite</a>
			<b>id.tipoTramite</b>
		</field>
	</mapping>
	
	<mapping>
		<class-a>org.gestoresmadrid.oegam2comun.vehiculo.view.dto.EvolucionVehiculoDto</class-a>
		<class-b>org.gestoresmadrid.core.vehiculo.model.vo.EvolucionVehiculoVO</class-b>
		<field>
			<a>idVehiculo</a>
			<b>id.idVehiculo</b>
		</field>
		<field>
			<a>numColegiado</a>
			<b>id.numColegiado</b>
		</field>
		<field>
			<a>fechaHora</a>
			<b>id.fechaHora</b>
		</field>
	</mapping>

	<mapping>
		<class-a>org.gestoresmadrid.oegamComun.tasa.view.dto.TasaDto</class-a>
		<class-b>org.gestoresmadrid.core.tasas.model.vo.TasaVO</class-b>
		<field>
			<a>usuario</a>
			<b>usuario</b>
		</field>
		<field>
			<a>contrato</a>
			<b>contrato</b>
		</field>
<!-- 		<field>
			<a>contrato.provinciaDto</a>
			<b>contrato.provincia</b>
		</field> -->
	</mapping>
	
	<mapping>
		<class-a>org.gestoresmadrid.oegamComun.tasa.view.dto.TasaDto</class-a>
		<class-b>org.gestoresmadrid.core.tasas.model.vo.TasaPegatinaVO</class-b>
		<field>
			<a>usuario</a>
			<b>usuario</b>
		</field>
		<field>
			<a>contrato</a>
			<b>contrato</b>
		</field>
		<field>
			<a>fechaAsignacion</a>
			<b>fechaFacturacion</b>
		</field>
	</mapping>
	
	<mapping>
		<class-a>org.gestoresmadrid.oegamComun.tasa.view.dto.TasaDto</class-a>
		<class-b>org.gestoresmadrid.core.tasas.model.vo.TasaMatwVO</class-b>
		<field>
			<a>tipoTramiteAlmacen</a>
			<b>tipoTramite</b>
		</field>
	</mapping>
	
	<mapping>
		<class-a>org.gestoresmadrid.oegam2comun.trafico.justificante.profesional.view.dto.EvolucionJustifProfesionalesDto</class-a>
		<class-b>org.gestoresmadrid.core.trafico.justificante.profesional.model.vo.EvolucionJustifProfesionalesVO</class-b>
		<field>
			<a>idJustificanteInterno</a>
			<b>id.idJustificanteInterno</b>
		</field>
		<field>
			<a>numExpediente</a>
			<b>id.numExpediente</b>
		</field>
		<field>
			<a>fechaCambio</a>
			<b>id.fechaCambio</b>
		</field>
		<field>
			<a>estadoAnterior</a>
			<b>id.estadoAnterior</b>
		</field>
		<field>
			<a>estado</a>
			<b>id.estado</b>
		</field>
		<field>
			<a>usuarioDto</a>
			<b>usuario</b>
		</field>
	</mapping>
	
	<mapping>
		<class-a>org.gestoresmadrid.oegam2comun.direccion.view.dto.PuebloDto</class-a>
		<class-b>org.gestoresmadrid.core.direccion.model.vo.PuebloVO</class-b>
		<field>
			<a>idProvincia</a>
			<b>id.idProvincia</b>
		</field>
		<field>
			<a>idMunicipio</a>
			<b>id.idMunicipio</b>
		</field>
		<field>
			<a>pueblo</a>
			<b>id.pueblo</b>
		</field>
	</mapping>
	
	<mapping>
		<class-a>org.gestoresmadrid.oegam2comun.vehiculo.view.dto.MarcaCamDto</class-a>
		<class-b>org.gestoresmadrid.core.vehiculo.model.vo.MarcaCamVO</class-b>
		<field>
			<a>cdMarca</a>
			<b>id.cdMarca</b>
		</field>
		<field>
			<a>tipVehi</a>
			<b>id.tipVehi</b>
		</field>
		<field>
			<a>fecDesde</a>
			<b>id.fecDesde</b>
		</field>
	</mapping>
	
	<mapping>
		<class-a>org.gestoresmadrid.oegam2comun.vehiculo.view.dto.MarcaFabricanteDto</class-a>
		<class-b>org.gestoresmadrid.core.vehiculo.model.vo.MarcaFabricanteVO</class-b>
		<field>
			<a>codigoMarca</a>
			<b>id.codigoMarca</b>
		</field>
		<field>
			<a>codFabricante</a>
			<b>id.codFabricante</b>
		</field>
	</mapping>
	
	<mapping>
		<class-a>org.gestoresmadrid.oegam2comun.vehiculo.view.dto.ModeloCamDto</class-a>
		<class-b>org.gestoresmadrid.core.vehiculo.model.vo.ModeloCamVO</class-b>
		<field>
			<a>cdMarca</a>
			<b>id.cdMarca</b>
		</field>
		<field>
			<a>tipVehi</a>
			<b>id.tipVehi</b>
		</field>
		<field>
			<a>fecDesde</a>
			<b>id.fecDesde</b>
		</field>
		<field>
			<a>cdModVeh</a>
			<b>id.cdModVeh</b>
		</field>
	</mapping>
	
  	<mapping>
  		<class-a>org.gestoresmadrid.core.tasas.model.vo.CompraTasaVO</class-a>
  		<class-b>org.gestoresmadrid.oegam2comun.tasas.view.beans.ResumenCompraBean</class-b>
  		<field>
  			<a>contrato.idContrato</a>
  			<b>idContrato</b>
  		</field>
  		<field>
  			<a>contrato.cif</a>
  			<b>cifContrato</b>
  		</field>
  		<field>
  			<a>contrato.colegiado.alias</a>
  			<b>aliasColegiado</b>
  		</field>
  		<field>
  			<a>contrato.colegiado.usuario.apellidosNombre</a>
  			<b>apellidosColegiado</b>
  		</field>
		<field>
			<a>desgloseCompraTasas</a>
			<b>listaResumenCompraBean</b>
		</field>
  	</mapping>

  	<mapping>
  		<class-a>org.gestoresmadrid.core.tasas.model.vo.DesgloseCompraTasa</class-a>
  		<class-b>org.gestoresmadrid.oegam2comun.tasas.view.beans.TasasSolicitadasBean</class-b>
  		<field>
  			<a>tasaDgt.grupo</a>
  			<b>grupo</b>
  		</field>
  		<field>
  			<a>tasaDgt.tipo</a>
  			<b>tipo</b>
  		</field>
  		<field>
  			<a>tasaDgt.codigoTasa</a>
  			<b>codigoTasa</b>
  		</field>
  		<field>
  			<a>tasaDgt.importe</a>
  			<b>importe</b>
  		</field>
  		<field>
  			<a>tasaDgt.descripcion</a>
  			<b>descripcion</b>
  		</field>
  	</mapping>
  	
  	<mapping>
  		<class-a>org.gestoresmadrid.core.tasas.model.vo.TasaVO</class-a>
  		<class-b>org.gestoresmadrid.oegam2comun.tasas.view.beans.Tasa</class-b>
  		<field>
  			<a>contrato.idContrato</a>
  			<b>idContrato</b>
  		</field>
  		<field>
  			<a>usuario.idUsuario</a>
  			<b>idUsuario</b>
  		</field>
  	</mapping>
  	
  	
  	<mapping>
  		<class-a>org.gestoresmadrid.oegam2comun.view.dto.OficinaLiquidadora620Dto</class-a>
  		<class-b>org.gestoresmadrid.core.general.model.vo.OficinaLiquidadora620VO</class-b>
  		<field>
  			<a>oficinaLiquidadora</a>
  			<b>id.oficinaLiquidadora</b>
  		</field>
  		<field>
  			<a>idProvincia</a>
  			<b>id.idProvincia</b>
  		</field>
  	</mapping>
  	
  	<mapping>
		<class-a>org.gestoresmadrid.oegam2comun.registradores.view.dto.SociedadCargoDto</class-a>
		<class-b>org.gestoresmadrid.core.registradores.model.vo.SociedadCargoVO</class-b>
		<field>
			<a>nifCargo</a>
			<b>id.nifCargo</b>
		</field>
		<field>
			<a>cifSociedad</a>
			<b>id.cifSociedad</b>
		</field>
		<field>
			<a>numColegiado</a>
			<b>id.numColegiado</b>
		</field>
		<field>
			<a>codigoCargo</a>
			<b>id.codigoCargo</b>
		</field>
	</mapping>
	
	<mapping>
		<class-a>org.gestoresmadrid.oegam2comun.registradores.view.dto.CertifCargoDto</class-a>
		<class-b>org.gestoresmadrid.core.registradores.model.vo.CertifCargoVO</class-b>
		<field>
			<a>nifCargo</a>
			<b>id.nifCargo</b>
		</field>
		<field>
			<a>cifSociedad</a>
			<b>id.cifSociedad</b>
		</field>
		<field>
			<a>idTramiteRegistro</a>
			<b>id.idTramiteRegistro</b>
		</field>
		<field>
			<a>codigoCargo</a>
			<b>id.codigoCargo</b>
		</field>
	</mapping>
	
	<mapping>
		<class-a>org.gestoresmadrid.oegam2comun.registradores.view.dto.AsistenteDto</class-a>
		<class-b>org.gestoresmadrid.core.registradores.model.vo.AsistenteVO</class-b>
		<field>
			<a>idTramiteRegistro</a>
			<b>id.idTramiteRegistro</b>
		</field>
		<field>
			<a>cifSociedad</a>
			<b>id.cifSociedad</b>
		</field>
		<field>
			<a>nifCargo</a>
			<b>id.nifCargo</b>
		</field>
		<field>
			<a>codigoCargo</a>
			<b>id.codigoCargo</b>
		</field>
		<field>
			<a>idReunion</a>
			<b>id.idReunion</b>
		</field>
	</mapping>
	
	<mapping>
		<class-a>org.gestoresmadrid.oegam2comun.registradores.view.dto.ConvocatoriaDto</class-a>
		<class-b>org.gestoresmadrid.core.registradores.model.vo.ConvocatoriaVO</class-b>
		<field>
			<a>idReunion</a>
			<b>id.idReunion</b>
		</field>
		<field>
			<a>idTramiteRegistro</a>
			<b>id.idTramiteRegistro</b>
		</field>
	</mapping>
	
	<mapping>
		<class-a>org.gestoresmadrid.oegam2comun.registradores.view.dto.MedioConvocatoriaDto</class-a>
		<class-b>org.gestoresmadrid.core.registradores.model.vo.MedioConvocatoriaVO</class-b>
		<field>
			<a>idMedio</a>
			<b>id.idMedio</b>
		</field>
		<field>
			<a>idTramiteRegistro</a>
			<b>id.idTramiteRegistro</b>
		</field>
		<field>
			<a>idReunion</a>
			<b>id.idReunion</b>
		</field>
		<field>
			<a>fechaPublicacion</a>
			<b>id.fechaPublicacion</b>
		</field>
	</mapping>	
	
	<mapping>
		<class-a>org.gestoresmadrid.oegam2comun.registradores.view.dto.OperacionRegistroDto</class-a>
		<class-b>org.gestoresmadrid.core.registradores.model.vo.OperacionRegistroVO</class-b>
		<field>
			<a>codigo</a>
			<b>id.codigo</b>
		</field>
		<field>
			<a>tipoTramite</a>
			<b>id.tipoTramite</b>
		</field>
	</mapping>
	
	<mapping>
		<class-a>org.gestoresmadrid.core.modelos.model.vo.OficinaLiquidadoraVO</class-a>
		<class-b>org.gestoresmadrid.oegam2comun.modelos.view.dto.OficinaLiquidadoraDto</class-b>
		<field>
			<a>id.oficinaLiquidadora</a>
			<b>id</b>
		</field>
		<field>
			<a>id.idProvincia</a>
			<b>idProvincia</b>
		</field>
	</mapping>
	
	<mapping>
		<class-a>org.gestoresmadrid.core.tipoInmueble.model.vo.TipoInmuebleVO</class-a>
		<class-b>org.gestoresmadrid.oegam2comun.tipoInmueble.view.dto.TipoInmuebleDto</class-b>
		<field>
			<a>id.idTipoBien</a>
			<b>idTipoBien</b>
		</field>
		<field>
			<a>id.idTipoInmueble</a>
			<b>idTipoInmueble</b>
		</field>
	</mapping>
	<mapping>
		<class-a>org.gestoresmadrid.core.modelos.model.vo.ModeloVO</class-a>
		<class-b>org.gestoresmadrid.oegam2comun.modelos.view.dto.ModeloDto</class-b>
		<field>
			<a>id.modelo</a>
			<b>modelo</b>
		</field>
		<field>
			<a>id.version</a>
			<b>version</b>
		</field>
	</mapping>
	<mapping>
		<class-a>org.gestoresmadrid.core.modelos.model.vo.ConceptoVO</class-a>
		<class-b>org.gestoresmadrid.oegam2comun.modelos.view.dto.ConceptoDto</class-b>
		<field>
			<a>id.modelo</a>
			<b>modelo.modelo</b>
		</field>
		<field>
			<a>id.version</a>
			<b>modelo.version</b>
		</field>
		<field>
			<a>id.concepto</a>
			<b>concepto</b>
		</field>
	</mapping>
	<mapping>
		<class-a>org.gestoresmadrid.oegam2comun.intervinienteModelos.view.dto.IntervinienteModelosDto</class-a>
		<class-b>org.gestoresmadrid.core.intervinienteModelos.model.vo.IntervinienteModelosVO</class-b>
		<field>
			<a>remesa</a>
			<b>remesa</b>
		</field>
		<field>
			<a>modelo600_601</a>
			<b>modelo600_601</b>
		</field>
		<field>
			<a>persona</a>
			<b>persona</b>
		</field>
		<field>
			<a>tipoInterviniente</a>
			<b>tipoInterviniente</b>
		</field>
		<field>
			<a>idInterviniente</a>
			<b>idInterviniente</b>
		</field>
		<field>
			<a>persona.nif</a>
			<b>nif</b>
		</field>
		<field>
			<a>persona.numColegiado</a>
			<b>numColegiado</b>
		</field>
		<field>
			<a>direccion</a>
			<b>direccion</b>
		</field>
	</mapping>
	<mapping>
		<class-a>org.gestoresmadrid.oegam2comun.bien.view.dto.BienDto</class-a>
		<class-b>org.gestoresmadrid.core.bien.model.vo.BienUrbanoVO</class-b>
		<field custom-converter-id="dozerBooleanToBigDecimalConverter">
			<a>arrendamiento</a>
			<b>arrendamiento</b>
		</field>
		<field custom-converter-id="dozerBooleanToBigDecimalConverter">
			<a>viviendaProtOficial</a>
			<b>viviendaProtOficial</b>
		</field>
		<field custom-converter-id="dozerBooleanToBigDecimalConverter">
			<a>descalificado</a>
			<b>descalificado</b>
		</field>
		<field custom-converter-id="dozerBooleanToBigDecimalConverter">
			<a>viHabitual</a>
			<b>viHabitual</b>
		</field>
	</mapping>
	<mapping>
		<class-a>org.gestoresmadrid.oegam2comun.remesa.view.dto.RemesaDto</class-a>
		<class-b>org.gestoresmadrid.core.remesa.model.vo.RemesaVO</class-b>
		<field custom-converter-id="dozerBooleanToBigDecimalConverter">
			<a>liquidacionComplementaria</a>
			<b>liquidacionComplementaria</b>
		</field>
		<field custom-converter-id="dozerBooleanToBigDecimalConverter">
			<a>exento</a>
			<b>exento</b>
		</field>
		<field custom-converter-id="dozerBooleanToBigDecimalConverter">
			<a>noSujeto</a>
			<b>noSujeto</b>
		</field>
		<field custom-converter-id="dozerBooleanToBigDecimalConverter">
			<a>protocoloBis</a>
			<b>protocoloBis</b>
		</field>
		<field>
			<a>concepto.concepto</a>
			<b>idConcepto</b>
		</field>
		<field>
			<a>referenciaPropia</a>
			<b>referenciaPropia</b>
		</field>
	</mapping>
	<mapping>
		<class-a>org.gestoresmadrid.oegam2comun.modelo600_601.view.dto.Modelo600_601Dto</class-a>
		<class-b>org.gestoresmadrid.core.modelo600_601.model.vo.Modelo600_601VO</class-b>
		<field custom-converter-id="dozerBooleanToBigDecimalConverter">
			<a>liquidacionComplementaria</a>
			<b>liquidacionComplementaria</b>
		</field>
		<field custom-converter-id="dozerBooleanToBigDecimalConverter">
			<a>exento</a>
			<b>exento</b>
		</field>
		<field custom-converter-id="dozerBooleanToBigDecimalConverter">
			<a>noSujeto</a>
			<b>noSujeto</b>
		</field>
		<field custom-converter-id="dozerBooleanToBigDecimalConverter">
			<a>protocoloBis</a>
			<b>protocoloBis</b>
		</field>
		<field custom-converter-id="dozerBooleanToBigDecimalConverter">
			<a>prescrito</a>
			<b>prescrito</b>
		</field>
		<field custom-converter-id="dozerBigDecimalToStringConverter">
			<a>baseImponible</a>
			<b>baseImponible</b>
		</field>
		<field custom-converter-id="dozerBigDecimalToStringConverter">
			<a>baseLiquidable</a>
			<b>baseLiquidable</b>
		</field>
		<field custom-converter-id="dozerBigDecimalToStringConverter">
			<a>valorTipoImpuesto</a>
			<b>tipoImpuesto.monto</b>
		</field>
		<field custom-converter-id="dozerBigDecimalToStringConverter">
			<a>cuota</a>
			<b>cuota</b>
		</field>
		<field custom-converter-id="dozerBigDecimalToStringConverter">
			<a>bonificacionCuota</a>
			<b>bonificacionCuota</b>
		</field>
		<field custom-converter-id="dozerBigDecimalToStringConverter">
			<a>ingresar</a>
			<b>ingresar</b>
		</field>
		<field custom-converter-id="dozerBigDecimalToStringConverter">
			<a>totalIngresar</a>
			<b>totalIngresar</b>
		</field>
		<field>
			<a>concepto.concepto</a>
			<b>idConcepto</b>
		</field>
		<field>
			<a>listaResultadoModelo</a>
			<b>listaResultadoModelo</b>
		</field>
		<field>
			<a>contrato.idContrato</a>
			<b>idContrato</b>
		</field>
		<field>
			<a>referenciaPropia</a>
			<b>referenciaPropia</b>
		</field>
	</mapping>
	<mapping>
		<class-a>org.gestoresmadrid.core.evolucionRemesas.model.vo.EvolucionRemesasVO</class-a>
		<class-b>org.gestoresmadrid.oegam2comun.evolucionRemesa.view.dto.EvolucionRemesasDto</class-b>
		<field>
			<a>id.numExpediente</a>
			<b>numExpediente</b>
		</field>
		<field>
			<a>id.fechaCambio</a>
			<b>fechaCambio</b>
		</field>
		<field>
			<a>id.estadoAnterior</a>
			<b>estadoAnterior</b>
		</field>
		<field>
			<a>id.estadoNuevo</a>
			<b>estadoNuevo</b>
		</field>
	</mapping>
	<mapping>
		<class-a>org.gestoresmadrid.core.evolucionModelo600601.model.vo.EvolucionModelo600_601VO</class-a>
		<class-b>org.gestoresmadrid.oegam2comun.evolucionModelo600601.view.dto.EvolucionModelo600_601Dto</class-b>
		<field>
			<a>id.numExpediente</a>
			<b>numExpediente</b>
		</field>
		<field>
			<a>id.fechaCambio</a>
			<b>fechaCambio</b>
		</field>
		<field>
			<a>id.estadoAnterior</a>
			<b>estadoAnterior</b>
		</field>
		<field>
			<a>id.estadoNuevo</a>
			<b>estadoNuevo</b>
		</field>
	</mapping>
	<mapping>
		<class-a>org.gestoresmadrid.core.datosBancariosFavoritos.model.vo.DatosBancariosFavoritosVO</class-a>
		<class-b>org.gestoresmadrid.oegam2comun.datosBancariosFavoritos.view.dto.DatosBancariosFavoritosDto</class-b>
		<field custom-converter-id="dozerBigDecimalToStringConverter">
			<a>formaPago</a>
			<b>formaPago</b>
		</field>
		<field custom-converter-id="dozerBigDecimalToStringConverter">
			<a>estado</a>
			<b>estado</b>
		</field>
		<field>
  			<a>idContrato</a>
  			<b>contrato.idContrato</b>
  		</field>
	</mapping>
	<mapping>
		<class-a>org.gestoresmadrid.oegam2comun.direccion.view.dto.MunicipioCamDto</class-a>
		<class-b>org.gestoresmadrid.core.direccion.model.vo.MunicipioCamVO</class-b>
		<field>
			<a>idMunicipio</a>
			<b>id.idMunicipio</b>
		</field>
		<field>
			<a>idProvincia</a>
			<b>id.idProvincia</b>
		</field>
	</mapping>
	<mapping>
		<class-a>org.gestoresmadrid.oegam2comun.creditos.view.dto.CreditoDto</class-a>
		<class-b>org.gestoresmadrid.core.general.model.vo.CreditoVO</class-b>
		<field>
			<a>idContrato</a>
			<b>id.idContrato</b>
		</field>
		<field>
			<a>tipoCredito</a>
			<b>id.tipoCredito</b>
		</field>
	</mapping>
	<mapping>
		<class-a>org.gestoresmadrid.core.bien.model.vo.BienVO</class-a>
		<class-b>org.gestoresmadrid.oegam2comun.bien.view.bean.BienBean</class-b>
		<field>
			<a>tipoInmueble.id.idTipoBien</a>
			<b>tipoBien</b>
		</field>
		<field>
			<a>tipoInmueble.descTipoInmueble</a>
			<b>tipoInmueble</b>
		</field>
		<field>
			<a>direccion.nombreVia</a>
			<b>nombreVia</b>
		</field>
	</mapping>
	<mapping>
  		<class-a>org.gestoresmadrid.oegam2comun.trafico.view.dto.DatosCardMatwDto</class-a>
		<class-b>org.gestoresmadrid.core.trafico.model.vo.TramiteTrafMatrVO</class-b>
		<field>
			<a>serialNumber</a>
			<b>vehiculo.bastidor</b>
		</field>
		<field>
			<a>form05Key</a>
			<b>idReduccion05</b>
		</field>
		<field>
			<a>form06ExcemptionType</a>
			<b>idNoSujeccion06</b>
		</field>
		<field>
			<a>agentFiscalId</a>
			<b>contrato.colegiado.usuario.nif</b>
		</field>
		<field>
			<a>serialCardITV</a>
			<b>vehiculo.nSerie</b>
		</field>
		<field>
			<a>externalSystemFiscalId</a>
			<b>contrato.colegio.cif</b>
		</field>
  	</mapping>
  	<mapping>
  		<class-a>org.gestoresmadrid.oegam2comun.trafico.view.dto.DatosCTITDto</class-a>
		<class-b>org.gestoresmadrid.core.trafico.model.vo.TramiteTrafTranVO</class-b>
		<field>
			<a>agencyFiscalId</a>
			<b>contrato.colegiado.usuario.nif</b>
		</field>
		<field>
			<a>externalSystemFiscalID</a>
			<b>contrato.colegio.cif</b>
		</field>
		<field>
			<a>pasos</a>
			<b>npasos</b>
		</field>
		<field>
			<a>numColegiado</a>
			<b>numColegiado</b>
		</field>
		<field>
			<a>plazas</a>
			<b>vehiculo.plazas</b>
		</field>
		<field>
			<a>idServicio</a>
			<b>vehiculo.idServicioAnterior</b>
		</field>
		<field>
			<a>pesoMma</a>
			<b>vehiculo.pesoMma</b>
		</field>
		<field>
			<a>tara</a>
			<b>vehiculo.tara</b>
		</field>
  	</mapping>
   	<mapping map-null="false">
  		<class-a>org.gestoresmadrid.oegam2comun.trafico.view.dto.TramiteTrafTranDto</class-a>
		<class-b>org.gestoresmadrid.core.trafico.model.vo.TramiteTrafTranVO</class-b>
		<field>
			<a>tipoReduccion.tipoReduccion</a>
			<b>tipoReduccion</b>
		</field>
		<field>
			<a>tipoMotor.tipoMotor</a>
			<b>tipoMotor</b>
		</field>
		<field>
			<a>codigoTasaInf</a>
			<b>tasa1.codigoTasa</b>
		</field>
		<field>
			<a>codigoTasaCamser</a>
			<b>tasa2.codigoTasa</b>
		</field>
  	</mapping>
  	<mapping>
  		<class-a>org.gestoresmadrid.oegam2comun.trafico.view.dto.TramiteTrafDuplicadoDto</class-a>
  		<class-b>org.gestoresmadrid.core.trafico.model.vo.TramiteTrafDuplicadoVO</class-b>
  		<field custom-converter-id="dozerSINOConverter">
  			<a>importacion</a>
  			<b>importacion</b>
  		</field>
  		<field custom-converter-id="dozerSINOConverter">
  			<a>imprPermisoCirculacion</a>
  			<b>imprPermisoCirculacion</b>
  		</field>
  	</mapping>
  	<mapping>
  		<class-a>org.gestoresmadrid.oegam2comun.trafico.view.dto.TramiteTrafCambioServicioDto</class-a>
  		<class-b>org.gestoresmadrid.core.trafico.model.vo.TramiteTrafCambioServicioVO</class-b>
  		<field custom-converter-id="dozerSINOConverter">
  			<a>imprPermisoCirculacion</a>
  			<b>imprPermisoCirculacion</b>
  		</field>
  		<field>
			<a>idContrato</a>
			<b>contrato.idContrato</b>
		</field>
  	</mapping>
  	<mapping>
		<class-a>org.gestoresmadrid.oegam2comun.tasas.view.beans.CertificadoTasasBean</class-a>
		<class-b>org.gestoresmadrid.oegam2comun.tasas.view.beans.IreportTablaCertificadoTasasBean</class-b>
		<field>
			<a>tasa.codigoTasa</a>
			<b>codigoTasa</b>
		</field>
		<field custom-converter-id="dozerBigDecimalToStringConverter">
			<a>tasa.precio</a>
			<b>importeTasa</b>
		</field>
		<field>
			<a>matricula</a>
			<b>matricula</b>
		</field>
		<field>
			<a>tasa.tipoTasa</a>
			<b>tipoTasa</b>
		</field>
	</mapping>
	<mapping>
		<class-a>org.gestoresmadrid.core.evolucionDatosBancariosFavoritos.modelo.vo.EvolucionDatosBancariosFavoritosVO</class-a>
		<class-b>org.gestoresmadrid.oegam2comun.evolucionDatosBancariosFavoritos.view.beans.EvolucionDatosBancariosFavoritosBean</class-b>
		<field>
			<a>usuario.apellidosNombre</a>
			<b>apellidosNombre</b>
		</field>
		<field>
			<a>id.fechaCambio</a>
			<b>fechaCambio</b>
		</field>
	</mapping>
	<mapping>
		<class-a>org.gestoresmadrid.core.contrato.model.vo.ContratoVO</class-a>
		<class-b>org.gestoresmadrid.oegam2comun.contrato.view.bean.ContratoBean</class-b>
		<field>
			<a>provincia.nombre</a>
			<b>provincia</b>
		</field>
		<field>
			<a>colegiado.numColegiado</a>
			<b>numColegiado</b>
		</field>
		<field>
			<a>colegiado.alias</a>
			<b>alias</b>
		</field>
	</mapping>
	<mapping>
		<class-a>org.gestoresmadrid.core.intervinienteTrafico.model.vo.IntervinienteTraficoVO</class-a>
		<class-b>org.gestoresmadrid.oegam2comun.intervinienteTrafico.view.bean.IntervinienteTraficoBean</class-b>
		<field>
			<a>id.nif</a>
			<b>nif</b>
		</field>
		<field>
			<a>id.numColegiado</a>
			<b>numColegiado</b>
		</field>
		<field>
			<a>id.numExpediente</a>
			<b>numExpediente</b>
		</field>
		<field>
			<a>id.tipoInterviniente</a>
			<b>tipoInterviniente</b>
		</field>
	</mapping>
	<mapping>
		<class-a>org.gestoresmadrid.core.consultaDev.model.vo.ConsultaDevVO</class-a>
		<class-b>org.gestoresmadrid.oegam2comun.consultaDev.model.dto.ConsultaDevDto</class-b>
		<field custom-converter-id="dozerBigDecimalToStringConverter">
			<a>estado</a>
			<b>estado</b>
		</field>
		<field custom-converter-id="dozerBigDecimalToStringConverter">
			<a>estadoCif</a>
			<b>estadoCif</b>
		</field>
		<field>
			<a>idContrato</a>
			<b>contrato.idContrato</b>
		</field>
	</mapping>
	<mapping>
		<class-a>es.dgt.www.nostra.esquemas.consultaDEV.datos_especificos.Suscripcion</class-a>
		<class-b>org.gestoresmadrid.core.consultaDev.model.vo.SuscripcionDevVO</class-b>
		<field>
			<a>desProcedimiento</a>
			<b>descProcedimiento</b>
		</field>
		<field-exclude>
			<a>codEstado</a>
			<b>codEstado</b>
		</field-exclude>
		<field-exclude>
			<a>fechaSuscripcion</a>
			<b>fechaSuscripcion</b>
		</field-exclude>
	</mapping>
	<mapping>
		<class-a>org.gestoresmadrid.core.evolucionConsultaDev.model.vo.EvolucionConsultaDevVO</class-a>
		<class-b>org.gestoresmadrid.oegam2comun.evolucionConsultaDev.view.dto.EvolucionConsultaDevDto</class-b>
		<field>
			<a>id.idConsultaDev</a>
			<b>idConsultaDev</b>
		</field>
		<field>
			<a>id.fechaCambio</a>
			<b>fechaCambio</b>
		</field>
		<field>
			<a>id.idUsuario</a>
			<b>idUsuario</b>
		</field>
	</mapping>
	<mapping>
		<class-a>org.gestoresmadrid.core.atex5.model.vo.ConsultaPersonaAtex5VO</class-a>
		<class-b>org.gestoresmadrid.oegam2comun.atex5.view.bean.ConsultaPersonaAtex5Bean</class-b>
		<field-exclude>
			<a>estado</a>
			<b>estado</b>
		</field-exclude>
	</mapping>
	<mapping>
		<class-a>org.gestoresmadrid.core.atex5.model.vo.ConsultaVehiculoAtex5VO</class-a>
		<class-b>org.gestoresmadrid.oegam2comun.atex5.view.bean.ConsultaVehiculoAtex5Bean</class-b>
		<field-exclude>
			<a>estado</a>
			<b>estado</b>
		</field-exclude>
		<field>
			<a>contrato.provincia.nombre</a>
			<b>provinciaContrato</b>
		</field>
	</mapping>
	<mapping>
		<class-a>org.gestoresmadrid.core.atex5.model.vo.ConsultaPersonaAtex5VO</class-a>
		<class-b>org.gestoresmadrid.oegam2comun.atex5.view.dto.ConsultaPersonaAtex5Dto</class-b>
		<field>
			<a>idContrato</a>
			<b>contrato.idContrato</b>
		</field>
		<field custom-converter-id="dozerBigDecimalToStringConverter">
			<a>estado</a>
			<b>estado</b>
		</field>
	</mapping>
	<mapping>
		<class-a>org.gestoresmadrid.core.atex5.model.vo.ConsultaVehiculoAtex5VO</class-a>
		<class-b>org.gestoresmadrid.oegam2comun.atex5.view.dto.ConsultaVehiculoAtex5Dto</class-b>
		<field>
			<a>idContrato</a>
			<b>contrato.idContrato</b>
		</field>
		<field custom-converter-id="dozerBigDecimalToStringConverter">
			<a>estado</a>
			<b>estado</b>
		</field>
	</mapping>
	<mapping>
		<class-a>org.gestoresmadrid.core.evolucionAtex5.model.vo.EvolucionAtex5VO</class-a>
		<class-b>org.gestoresmadrid.oegam2comun.evolucionAtex5.view.dto.EvolucionAtex5Dto</class-b>
		<field>
			<a>id.numExpediente</a>
			<b>numExpediente</b>
		</field>
		<field>
			<a>id.fechaCambio</a>
			<b>fechaCambio</b>
		</field>
		<field>
			<a>id.idUsuario</a>
			<b>idUsuario</b>
		</field>
	</mapping>
	<mapping>
		<class-a>org.gestoresmadrid.core.atex5.model.vo.ConsultaPersonaAtex5VO</class-a>
		<class-b>es.trafico.servicios.vehiculos.consulta.atex.webservices.SolicitudConsultaPersonaAtex</class-b>
		<field>
			<a>contrato.colegiado.usuario.nif</a>
			<b>idResponsable</b>
		</field>
		<field>
			<a>contrato.colegio.cif</a>
			<b>idUsuario</b>
		</field>
		<field>
			<a>nif</a>
			<b>criteriosConsultaPersona.doi</b>
		</field>
		<field>
			<a>nombre</a>
			<b>criteriosConsultaPersona.nombre</b>
		</field>
		<field>
			<a>apellido1</a>
			<b>criteriosConsultaPersona.primerApellido</b>
		</field>
		<field>
			<a>apellido2</a>
			<b>criteriosConsultaPersona.segundoApellido</b>
		</field>
		<field>
			<a>razonSocial</a>
			<b>criteriosConsultaPersona.razonSocial</b>
		</field>
		<field>
			<a>anioNacimiento</a>
			<b>criteriosConsultaPersona.anyoNacimiento</b>
		</field>
	</mapping>
	<mapping>
		<class-a>org.gestoresmadrid.oegam2comun.trafico.eeff.view.dto.ConsultaEEFFDto</class-a>
		<class-b>org.gestoresmadrid.core.trafico.eeff.model.vo.ConsultaEEFFVO</class-b>
		<field>
			<a>contrato.idContrato</a>
			<b>idContrato</b>
		</field>
	</mapping>
	<mapping>
		<class-a>trafico.beans.jaxb.matw.FORMATOGA.MATRICULACION</class-a>
		<class-b>org.gestoresmadrid.core.trafico.eeff.model.vo.LiberacionEEFFVO</class-b>
		<field>
			<a>numeroexpediente</a>
			<b>numExpediente</b>
		</field>
		<field>
			<a>NUMEROPROFESIONAL</a>
			<b>numColegiado</b>
		</field>
		<field>
			<a>datosvehiculo.nive</a>
			<b>tarjetaNive</b>
		</field>
		<field>
			<a>datosvehiculo.numerobastidor</a>
			<b>tarjetaBastidor</b>
		</field>
		<field>
			<a>datosliberacion.ciffir</a>
			<b>firCif</b>
		</field>
		<field>
			<a>datosliberacion.marcafir</a>
			<b>firMarca</b>
		</field>
		<field>
			<a>datosliberacion.numfactura</a>
			<b>numFactura</b>
		</field>
		<field>
			<a>datosliberacion.nifrepresentado</a>
			<b>nifRepresentado</b>
		</field>
	</mapping>
	<mapping>
		<class-a>org.gestoresmadrid.oegam2comun.transporte.view.dto.NotificacionTransporteDto</class-a>
		<class-b>org.gestoresmadrid.core.transporte.model.vo.NotificacionTransporteVO</class-b>
		<field>
			<a>contrato.idContrato</a>
			<b>idContrato</b>
		</field>
		<field>
			<a>usuario.idUsuario</a>
			<b>idUsuario</b>
		</field>
	</mapping>
	<mapping>
		<class-a>org.gestoresmadrid.oegam2comun.transporte.view.dto.PoderTransporteDto</class-a>
		<class-b>org.gestoresmadrid.core.transporte.model.vo.PoderTransporteVO</class-b>
		<field>
			<a>contrato.idContrato</a>
			<b>idContrato</b>
		</field>
	</mapping>
	<mapping>
		<class-a>org.gestoresmadrid.core.trafico.justificante.profesional.model.vo.JustificanteProfVO</class-a>
		<class-b>org.gestoresmadrid.oegam2comun.trafico.justificante.profesional.view.beans.ConsultaJustificantePantallaBean</class-b>
		<field>
			<a>tramiteTrafico.vehiculo.matricula</a>
			<b>matricula</b>
		</field>
		<field>
			<a>tramiteTrafico.numColegiado</a>
			<b>numColegiado</b>
		</field>
		<field>
			<a>tramiteTrafico.tipoTramite</a>
			<b>tipoTramite</b>
		</field>
		<field-exclude>
			<a>fechaFin</a>
			<b>fechaFin</b>
		</field-exclude>
	</mapping>
	<mapping>
		<class-a>org.gestoresmadrid.oegam2comun.atex5.xml.vehiculo.Domicilio</class-a>
		<class-b>org.gestoresmadrid.oegam2comun.atex5.view.dto.DatosDomicilioAtex5Dto</class-b>
		<field>
			<a>calle</a>
			<b>via</b>
		</field>
		<field>
			<a>provincia.descripcion</a>
			<b>provincia</b>
		</field>
	</mapping>
	<mapping>
		<class-a>org.gestoresmadrid.oegam2comun.atex5.xml.vehiculo.Cotitular</class-a>
		<class-b>org.gestoresmadrid.oegam2comun.atex5.view.dto.DatosCotitularAtex5Dto</class-b>
		<field>
			<a>idDocumento</a>
			<b>nifCotitular</b>
		</field>
		<field>
			<a>filiacion</a>
			<b>filiacionCotitular</b>
		</field>
	</mapping>
	<mapping>
		<class-a>org.gestoresmadrid.oegam2comun.atex5.xml.vehiculo.Arrendatario</class-a>
		<class-b>org.gestoresmadrid.oegam2comun.atex5.view.dto.DatosResponsableAtex5Dto</class-b>
		<field>
			<a>idDocumento</a>
			<b>nif</b>
		</field>
		<field-exclude>
			<a>fechaFin</a>
			<b>fechaFin</b>
		</field-exclude>
	</mapping>
	<mapping>
		<class-a>org.gestoresmadrid.oegam2comun.atex5.xml.vehiculo.ConductorHabitual</class-a>
		<class-b>org.gestoresmadrid.oegam2comun.atex5.view.dto.DatosResponsableAtex5Dto</class-b>
		<field>
			<a>idDocumento</a>
			<b>nif</b>
		</field>
		<field-exclude>
			<a>fechaFin</a>
			<b>fechaFin</b>
		</field-exclude>
	</mapping>
	<mapping>
		<class-a>org.gestoresmadrid.oegam2comun.atex5.xml.vehiculo.Poseedor</class-a>
		<class-b>org.gestoresmadrid.oegam2comun.atex5.view.dto.DatosResponsableAtex5Dto</class-b>
		<field>
			<a>idDocumento</a>
			<b>nif</b>
		</field>
		<field>
			<a>jefatura.descripcion</a>
			<b>jefatura</b>
		</field>
		<field>
			<a>situacionPosesion.descripcion</a>
			<b>situacionPosesion</b>
		</field>
		<field>
			<a>sucursal.descripcion</a>
			<b>sucursal</b>
		</field>
	</mapping>
	<mapping>
		<class-a>org.gestoresmadrid.oegam2comun.atex5.xml.vehiculo.Itv</class-a>
		<class-b>org.gestoresmadrid.oegam2comun.atex5.view.dto.DatosItvAtex5Dto</class-b>
		<field>
			<a>motivoItv.descripcion</a>
			<b>motivoItv</b>
		</field>
		<field>
			<a>provincia.descripcion</a>
			<b>provincia</b>
		</field>
		<field>
			<a>resultadoItv.descripcion</a>
			<b>resultadoItv</b>
		</field>
		<field-exclude>
			<a>fechaFinAnterior</a>
			<b>fechaFinAnterior</b>
		</field-exclude>
		<field-exclude>
			<a>fechaItv</a>
			<b>fechaItv</b>
		</field-exclude>
	</mapping>
	<mapping>
		<class-a>org.gestoresmadrid.oegam2comun.atex5.xml.vehiculo.DefectoItv</class-a>
		<class-b>org.gestoresmadrid.oegam2comun.atex5.view.dto.DatosDefectoItvAtex5Dto</class-b>
		<field>
			<a>gravedadDefectoItv.descripcion</a>
			<b>gravedadDefectoItv</b>
		</field>
		<field>
			<a>tipoDefectoItv.descripcion</a>
			<b>tipoDefectoItv</b>
		</field>
	</mapping>
	<mapping>
		<class-a>org.gestoresmadrid.oegam2comun.atex5.xml.vehiculo.Seguro</class-a>
		<class-b>org.gestoresmadrid.oegam2comun.atex5.view.dto.DatosSeguroAtex5Dto</class-b>
		<field>
			<a>contratoSeguro.descripcion</a>
			<b>contratoSeguro</b>
		</field>
		<field>
			<a>entidad.descripcion</a>
			<b>entidad</b>
		</field>
		<field-exclude>
			<a>fechaFin</a>
			<b>fechaFin</b>
		</field-exclude>
	</mapping>
	<mapping>
		<class-a>org.gestoresmadrid.oegam2comun.atex5.xml.persona.Permiso</class-a>
		<class-b>org.gestoresmadrid.oegam2comun.atex5.view.dto.DatosPermisoAtex5Dto</class-b>
		<field custom-converter-id="dozerXmlCalendarConverter">
			<a>fechaFin</a>
			<b>fechaFin</b>
		</field>
		<field custom-converter-id="dozerXmlCalendarConverter">
			<a>fechaInicio</a>
			<b>fechaInicio</b>
		</field>
		<field>
			<a>tipoPermiso.descripcion</a>
			<b>tipoPermiso</b>
		</field>
		<field custom-converter-id="dozerXmlCalendarConverter">
			<a>vigencia</a>
			<b>vigencia</b>
		</field>
	</mapping>
	<mapping>
		<class-a>org.gestoresmadrid.oegam2comun.atex5.xml.persona.DatosSanciones</class-a>
		<class-b>org.gestoresmadrid.oegam2comun.atex5.view.dto.DatosSancionPersonaAtex5Dto</class-b>
		<field custom-converter-id="dozerXmlCalendarConverter">
			<a>fecha</a>
			<b>fecha</b>
		</field>
		<field custom-converter-id="dozerXmlCalendarConverter">
			<a>fechaFin</a>
			<b>fechaFin</b>
		</field>
		<field>
			<a>autoridadSancionadora.descripcion</a>
			<b>autoridadSancionadora</b>
		</field>
		<field>
			<a>motivo.descripcion</a>
			<b>motivo</b>
		</field>
		<field>
			<a>tipoSancion.descripcion</a>
			<b>tipoSancion</b>
		</field>
	</mapping>
	<mapping>
		<class-a>org.gestoresmadrid.oegam2comun.atex5.xml.persona.PersonaFisica</class-a>
		<class-b>org.gestoresmadrid.oegam2comun.atex5.view.dto.DatosPersonaAtex5Dto</class-b>
		<field>
			<a>idDocumento</a>
			<b>nif</b>
		</field>
		<field custom-converter-id="dozerXmlCalendarConverter">
			<a>fechaNacimiento</a>
			<b>fechaNacimiento</b>
		</field>
	</mapping>
	<mapping>
		<class-a>org.gestoresmadrid.oegam2comun.atex5.xml.persona.Domicilio</class-a>
		<class-b>org.gestoresmadrid.oegam2comun.atex5.view.dto.DatosDomicilioAtex5Dto</class-b>
		<field>
			<a>calle</a>
			<b>via</b>
		</field>
		<field>
			<a>provincia.descripcion</a>
			<b>provincia</b>
		</field>
	</mapping>
	<mapping>
		<class-a>org.gestoresmadrid.oegam2comun.atex5.xml.persona.DomicilioIne</class-a>
		<class-b>org.gestoresmadrid.oegam2comun.atex5.view.dto.DatosDomicilioAtex5Dto</class-b>
		<field>
			<a>provincia.descripcion</a>
			<b>provincia</b>
		</field>
	</mapping>
	<mapping>
		<class-a>org.gestoresmadrid.oegam2comun.atex5.xml.vehiculo.DomicilioIne</class-a>
		<class-b>org.gestoresmadrid.oegam2comun.atex5.view.dto.DatosDomicilioAtex5Dto</class-b>
		<field>
			<a>provincia.descripcion</a>
			<b>provincia</b>
		</field>
	</mapping>
	<mapping>
  		<class-a>org.gestoresmadrid.oegam2comun.trafico.view.dto.TramiteTrafMatrDto</class-a>
		<class-b>net.gestores.sega.matw.MatwArgument</class-b>
		<field>
			<a>vehiculoDto.bastidor</a>
			<b>serialNumber</b>
		</field>
		<field>
			<a>idReduccion05</a>
			<b>form05Key</b>
		</field>
		<field>
			<a>contrato.colegiadoDto.usuario.nif</a>
			<b>agentFiscalId</b>
		</field>
		<field>
			<a>vehiculoDto.numSerie</a>
			<b>serialCardITV</b>
		</field>
		<field>
			<a>contrato.colegioDto.cif</a>
			<b>externalSystemFiscalId</b>
		</field>
  	</mapping>
  	<mapping>
  		<class-a>org.gestoresmadrid.core.evolucionDatosSensibles.model.vo.EvolucionDatosSensiblesBastidorVO</class-a>
  		<class-b>org.gestoresmadrid.oegam2comun.datosSensibles.views.beans.EvolucionDatosSensiblesBean</class-b>
  		<field>
  			<a>bastidor</a>
  			<b>num</b>
  		</field>
  		<field>
  			<a>usuario.apellidosNombre</a>
  			<b>apellidosNombre</b>
  		</field>
  	</mapping>
  	<mapping>
  		<class-a>org.gestoresmadrid.core.evolucionDatosSensibles.model.vo.EvolucionDatosSensiblesMatriculaVO</class-a>
  		<class-b>org.gestoresmadrid.oegam2comun.datosSensibles.views.beans.EvolucionDatosSensiblesBean</class-b>
  		<field>
  			<a>matricula</a>
  			<b>num</b>
  		</field>
  		<field>
  			<a>usuario.apellidosNombre</a>
  			<b>apellidosNombre</b>
  		</field>
  	</mapping>
  	<mapping>
  		<class-a>org.gestoresmadrid.core.evolucionDatosSensibles.model.vo.EvolucionDatosSensiblesNifVO</class-a>
  		<class-b>org.gestoresmadrid.oegam2comun.datosSensibles.views.beans.EvolucionDatosSensiblesBean</class-b>
  		<field>
  			<a>nif</a>
  			<b>num</b>
  		</field>
  		<field>
  			<a>usuario.apellidosNombre</a>
  			<b>apellidosNombre</b>
  		</field>
  	</mapping>
  	<mapping>
  		<class-a>org.gestoresmadrid.core.trafico.model.vo.TramiteTrafSolInfoVO</class-a>
  		<class-b>org.gestoresmadrid.oegam2comun.trafico.view.dto.TramiteTrafSolInfoDto</class-b>
  		<field>
  			<a>usuario</a>
  			<b>usuarioDto</b>
  		</field>
  	</mapping>
  	<mapping>
  		<class-a>org.gestoresmadrid.core.trafico.model.vo.TramiteTrafSolInfoVehiculoVO</class-a>
  		<class-b>org.gestoresmadrid.oegam2comun.trafico.view.dto.SolicitudInformeVehiculoDto</class-b>
		<field>
  			<a>id.numExpediente</a>
  			<b>tramiteTrafico.numExpediente</b>
  		</field>
  		<field>
  			<a>id.numColegiado</a>
  			<b>tramiteTrafico.numColegiado</b>
  		</field>
  		<field>
  			<a>id.idVehiculo</a>
  			<b>vehiculo.idVehiculo</b>
  		</field>
  		<field>
  			<a>codigoTasa</a>
  			<b>tasa.codigoTasa</b>
  		</field>
  	</mapping>
  	<mapping>
		<class-a>org.gestoresmadrid.core.arrendatarios.model.vo.ArrendatarioVO</class-a>
		<class-b>org.gestoresmadrid.oegam2comun.arrendatarios.view.dto.ArrendatarioDto</class-b>
		<field>
			<a>idContrato</a>
			<b>contrato.idContrato</b>
		</field>
		<field custom-converter-id="dozerBigDecimalToStringConverter">
			<a>estado</a>
			<b>estado</b>
		</field>
		<field>
			<a>nif</a>
			<b>persona.nif</b>
		</field>
		<field>
			<a>idDireccion</a>
			<b>persona.direccionDto.idDireccion</b>
		</field>		
	</mapping> 
	<mapping>
		<class-a>org.gestoresmadrid.core.conductor.model.vo.ConductorVO</class-a>
		<class-b>org.gestoresmadrid.oegam2comun.conductor.view.dto.ConductorDto</class-b>
		<field>
			<a>idContrato</a>
			<b>contrato.idContrato</b>
		</field>
		<field custom-converter-id="dozerBigDecimalToStringConverter">
			<a>estado</a>
			<b>estado</b>
		</field>
		<field>
			<a>nif</a>
			<b>persona.nif</b>
		</field>
						
	</mapping>
  	<mapping>
  		<class-a>org.gestoresmadrid.core.trafico.materiales.model.vo.PedidoVO</class-a>
  		<class-b>org.gestoresmadrid.oegam2comun.trafico.materiales.view.dto.PedidoDto</class-b>
		<field>
		    <a>jefaturaProvincial.jefaturaProvincial</a>
		    <b>jefaturaProvincial</b>
		</field>
		<field>
		    <a>jefaturaProvincial.descripcion</a>
		    <b>jefaturaDescripcion</b>
		</field>
		<field>
		    <a>autorVO.nombre</a>
		    <b>autorNombre</b>
		</field>
		<field>
		    <a>materialVO.materialId</a>
		    <b>materialId</b>
		</field>
		<field>
		    <a>materialVO.name</a>
		    <b>materialNombre</b>
		</field>
		<field>
		    <a>pedidoDgt</a>
		    <b>pedidoDgt</b>
		</field>
  	</mapping>

  	<mapping>
  		<class-a>org.gestoresmadrid.core.trafico.materiales.model.vo.IncidenciaVO</class-a>
  		<class-b>org.gestoresmadrid.oegam2comun.trafico.materiales.view.beans.IncidenciasResultadosBean</class-b>
		<field>
		    <a>materialVO.materialId</a>
		    <b>materialId</b>
		</field>
		<field>
		    <a>materialVO.name</a>
		    <b>name</b>
		</field>
		<field>
		    <a>jefaturaProvincial.jefaturaProvincial</a>
		    <b>jefaturaProvincial</b>
		</field>
		<field>
		    <a>jefaturaProvincial.descripcion</a>
		    <b>descripcion</b>
		</field>
		<field>
		    <a>autorVO.nombre</a>
		    <b>autor</b>
		</field>
  	</mapping> 
  	 
  	<mapping>
  		<class-a>org.gestoresmadrid.core.trafico.materiales.model.vo.IncidenciaVO</class-a>
  		<class-b>org.gestoresmadrid.oegam2comun.trafico.materiales.view.dto.IncidenciaDto</class-b>
		<field>
		    <a>materialVO.materialId</a>
		    <b>materiaId</b>
		</field>
		<field>
		    <a>materialVO.name</a>
		    <b>materiaNombre</b>
		</field>
		<field>
		    <a>fecha</a>
		    <b>fecha</b>
		</field>
		<field>
		    <a>estado</a>
		    <b>estadoInc</b>
		</field>
		<field>
		    <a>jefaturaProvincial.jefaturaProvincial</a>
		    <b>jefaturaProvincial</b>
		</field>
		<field>
		    <a>jefaturaProvincial.descripcion</a>
		    <b>jefaturaDescripcion</b>
		</field>
		<field>
		    <a>listaSeriales</a>
		    <b>listaSerial</b>
		</field>
		<field>
		    <a>listaIntervalos</a>
		    <b>listaIntervalos</b>
		</field>
  	</mapping> 
  	<mapping>
  		<class-a>org.gestoresmadrid.core.trafico.materiales.model.vo.IncidenciaSerialVO</class-a>
  		<class-b>org.gestoresmadrid.oegam2comun.trafico.materiales.view.dto.IncidenciaSerialDto</class-b>
		<field>
		    <a>pk.numSerie</a>
		    <b>numSerie</b>
		</field>
		<field>
		    <a>incidenciaInvId</a>
		    <b>incidenciaInve</b>
		</field>
  	</mapping> 
  	
  	<mapping>
  		<class-a>org.gestoresmadrid.core.trafico.materiales.model.vo.IncidenciaIntervaloVO</class-a>
  		<class-b>org.gestoresmadrid.oegam2comun.trafico.materiales.view.dto.IncidenciaIntervalosDto</class-b>
		<field>
		    <a>pk.numSerieIni</a>
		    <b>numSerieIni</b>
		</field>
		<field>
		    <a>numSerieFin</a>
		    <b>numSerieFin</b>
		</field>
  	</mapping>
  	 
  	<mapping>
  		<class-a>org.gestoresmadrid.oegam2comun.trafico.materiales.view.beans.rest.StockInfoRest</class-a>
  		<class-b>org.gestoresmadrid.oegam2comun.trafico.materiales.view.dto.MaterialStockDto</class-b>
		<field-exclude>
		    <a>jefaturaProvincial</a>
		    <b>jefaturaProvincial</b>
		</field-exclude>
		<field-exclude>
		    <a>fecUltRecarga</a>
		    <b>fecUltRecarga</b>
		</field-exclude>
		<field-exclude>
		    <a>fecUltConsumo</a>
		    <b>fecUltConsumo</b>
		</field-exclude>
  	</mapping> 
  	<mapping>
  		<class-a>org.gestoresmadrid.oegam2comun.trafico.materiales.view.beans.rest.PedidoInfoRest</class-a>
  		<class-b>org.gestoresmadrid.oegam2comun.trafico.materiales.view.dto.PedidoDto</class-b>
		<field-exclude>
		    <a>jefaturaProvincial</a>
		    <b>jefaturaProvincial</b>
		</field-exclude>
		<field-exclude>
		    <a>fecha</a>
		    <b>fecha</b>
		</field-exclude>
		<field-exclude>
		    <a>estado</a>
		    <b>estado</b>
		</field-exclude>
  	</mapping> 
  	<mapping>
  		<class-a>org.gestoresmadrid.oegam2comun.trafico.materiales.view.beans.rest.IncidenciaInfoRest</class-a>
  		<class-b>org.gestoresmadrid.oegam2comun.trafico.materiales.view.dto.IncidenciaDto</class-b>
  		<field>
		    <a>material.id</a>
		    <b>materiaId</b>
		</field>
  		<field>
		    <a>observaciones</a>
		    <b>observaciones</b>
		</field>
  		<field>
		    <a>tipo</a>
		    <b>tipo</b>
		</field>
  		<field>
		    <a>fecha</a>
		    <b>fecha</b>
		</field>
  		<field>
		    <a>fecha</a>
		    <b>fecha</b>
		</field>
		<field-exclude>
		    <a>jefaturaProvincial</a>
		    <b>jefaturaProvincial</b>
		</field-exclude>
		<field-exclude>
		    <a>fecha</a>
		    <b>fecha</b>
		</field-exclude>
  	</mapping>
  	<mapping>
  		<class-a>org.gestoresmadrid.oegam2comun.trafico.empresa.telematica.view.dto.EmpresaTelematicaDto</class-a>
  		<class-b>org.gestoresmadrid.core.trafico.empresa.telematica.model.vo.EmpresaTelematicaVO</class-b>
		<field custom-converter-id="dozerFechaConverter">
			<a>fechaAlta</a>
			<b>fechaAlta</b>
		</field>
		<field>
			<a>idContrato</a>
			<b>contratoVO.idContrato</b>
		</field>
		<field>
			<a>idContrato</a>
			<b>idContrato</b>
		</field>
		<field>
			<a>municipio</a>
			<b>municipio</b>
		</field>
		<field>
			<a>municipio</a>
			<b>municipioVO.id.idMunicipio</b>
		</field>
		<field>
			<a>provincia</a>
			<b>provinciaVO.idProvincia</b>
		</field>
		<field>
			<a>provincia</a>
			<b>provincia</b>
		</field>			
		<field>
			<a>provincia</a>
			<b>municipioVO.id.idProvincia</b>
		</field>	
  	</mapping>   	 

  	<mapping>
  		<class-a>org.gestoresmadrid.oegam2comun.trafico.materiales.view.beans.rest.UsuarioInfoRest</class-a>
  		<class-b>org.gestoresmadrid.core.trafico.materiales.model.vo.UsuarioColegioVO</class-b>
		<field>
		    <a>id</a>
		    <b>usuarioId</b>
		</field>
		<field>
		    <a>colegio.id</a>
		    <b>colegioVO.colegioId</b>
		</field>
		<field>
		    <a>colegio</a>
		    <b>colegioVO</b>
		</field>
		<field>
		    <a>delegacion</a>
		    <b>delegacionVO</b>
		</field>
  	</mapping> 
  	<mapping>
  		<class-a>org.gestoresmadrid.oegam2comun.trafico.materiales.view.beans.rest.ColegioRest</class-a>
  		<class-b>org.gestoresmadrid.core.trafico.materiales.model.vo.ColegioConsejoVO</class-b>
		<field>
		    <a>id</a>
		    <b>colegioId</b>
		</field>
		<field>
		    <a>nombre</a>
		    <b>colegioDes</b>
		</field>
  	</mapping> 
  	<mapping>
  		<class-a>org.gestoresmadrid.oegam2comun.trafico.materiales.view.beans.rest.DelegacionRest</class-a>
  		<class-b>org.gestoresmadrid.core.trafico.materiales.model.vo.DelegacionVO</class-b>
		<field>
		    <a>id</a>
		    <b>delegacionId</b>
		</field>
		<field>
		    <a>nombre</a>
		    <b>delegacionDes</b>
		</field>
  	</mapping> 
  	<mapping>
  		<class-a>org.gestoresmadrid.oegam2comun.trafico.materiales.view.beans.rest.MaterialInfoRest</class-a>
  		<class-b>org.gestoresmadrid.core.trafico.materiales.model.vo.MaterialVO</class-b>
		<field>
		    <a>id</a>
		    <b>materialId</b>
		</field>
		<field>
		    <a>nombre</a>
		    <b>name</b>
		</field>
  	</mapping> 
  	<mapping>
  		<class-a>org.gestoresmadrid.oegam2comun.trafico.materiales.view.beans.rest.StockInfoRest</class-a>
  		<class-b>org.gestoresmadrid.core.trafico.materiales.model.vo.MaterialStockVO</class-b>
		<field>
		    <a>id</a>
		    <b>stockInvId</b>
		</field>
		<field>
		    <a date-format="yyyy-MM-dd HH:mm:ss">fecha</a>
		    <b>fecUltRecarga</b>
		</field>
		<field>
		    <a>material</a>
		    <b>materialVO</b>
		</field>
  	</mapping> 
  	<mapping>
  		<class-a>org.gestoresmadrid.oegam2comun.trafico.materiales.view.beans.rest.PedidoInfoRest</class-a>
  		<class-b>org.gestoresmadrid.core.trafico.materiales.model.vo.PedidoVO</class-b>
		<field>
		    <a>id</a>
		    <b>pedidoInvId</b>
		</field>
		<field>
		    <a date-format="yyyy-MM-dd HH:mm:ss">fecha</a>
		    <b>fecha</b>
		</field>
		<field>
		    <a>codInicial</a>
		    <b>codigoInicial</b>
		</field>
		<field>
		    <a>codFinal</a>
		    <b>codigoFinal</b>
		</field>
		<field>
		    <a>material</a>
		    <b>materialVO</b>
		</field>
		<field>
		    <a>autor</a>
		    <b>autorVO</b>
		</field>
		<field-exclude>
		    <a>estado</a>
		    <b>estado</b>
		</field-exclude>
		<field-exclude>
		    <a>fecUltConsumo</a>
		    <b>fecUltConsumo</b>
		</field-exclude>
  	</mapping> 
  	<mapping>
  		<class-a>org.gestoresmadrid.oegam2comun.trafico.materiales.view.beans.rest.AutorRest</class-a>
  		<class-b>org.gestoresmadrid.core.trafico.materiales.model.vo.AutorVO</class-b>
		<field>
		    <a>id</a>
		    <b>autorId</b>
		</field>
  	</mapping> 
  	
  	<!--  TODO -->
  	<mapping>
  		<class-a>org.gestoresmadrid.oegam2comun.trafico.materiales.view.beans.EvolucionPedidoResultadosBean</class-a>
  		<class-b>org.gestoresmadrid.core.trafico.materiales.model.vo.EvolucionPedidoVO</class-b>
		<field>
		    <a>pedidoId</a>
		    <b>pedidoVO.pedidoId</b>
		</field>
		<field>
		    <a>inventarioId</a>
		    <b>pedidoInvId</b>
		</field>
		<field>
		    <a>estadoInicial</a>
		    <b>estadoInicial</b>
		</field>
		<field>
		    <a>estado</a>
		    <b>estadoFinal</b>
		</field>
		<field>
		    <a date-format="yyyy-MM-dd HH:mm:ss">fecha</a>
		    <b>fecha</b>
		</field>
  	</mapping> 
  	
  	<mapping>
  		<class-a>org.gestoresmadrid.oegam2comun.trafico.materiales.view.beans.rest.IncidenciaInfoRest</class-a>
  		<class-b>org.gestoresmadrid.core.trafico.materiales.model.vo.IncidenciaVO</class-b>
		<field>
		    <a date-format="yyyy-MM-dd HH:mm:ss">fecha</a>
		    <b>fecha</b>
		</field>
		<field>
		    <a>material</a>
		    <b>materialVO</b>
		</field>
		<field>
		    <a>autor</a>
		    <b>autorVO</b>
		</field>
		<field>
		    <a>tipo</a>
		    <b>tipo</b>
		</field>
  	</mapping> 
  	<mapping>
		<class-a>org.gestoresmadrid.core.mandato.model.vo.EvolucionMandatoVO</class-a>
		<class-b>org.gestoresmadrid.oegam2comun.mandato.view.dto.EvolucionMandatoDto</class-b>
		<field>
			<a>id.idMandato</a>
			<b>idMandato</b>
		</field>
		<field>
			<a>id.fechaCambio</a>
			<b>fechaCambio</b>
		</field>
		<field>
			<a>id.idUsuario</a>
			<b>idUsuario</b>
		</field>
	</mapping>
  	<mapping>
		<class-a>org.gestoresmadrid.core.docPermDistItv.model.vo.VehNoMatOegamVO</class-a>
		<class-b>org.gestoresmadrid.oegam2comun.distintivo.view.dto.VehiculoNoMatriculadoOegamDto</class-b>
		<field>
			<a>idContrato</a>
			<b>contrato.idContrato</b>
		</field>
	</mapping>
	<mapping>
		<class-a>org.gestoresmadrid.core.proceso.model.vo.ProcesoVO</class-a>
		<class-b>org.gestoresmadrid.oegam2comun.proceso.view.dto.ProcesoDto</class-b>
		<field>
			<a>id.proceso</a>
			<b>proceso</b>
		</field>
		<field>
			<a>id.nodo</a>
			<b>nodo</b>
		</field>
	</mapping>
		<mapping>
		<class-a>org.gestoresmadrid.core.circular.model.vo.CircularVO</class-a>
		<class-b>org.gestoresmadrid.oegam2comun.circular.view.dto.CircularDto</class-b>
			<field custom-converter-id="dozerBooleanToBigDecimalConverter">
			<a>repeticiones</a>
			<b>repeticiones</b>
		</field>
			<field custom-converter-id="dozerBooleanToBigDecimalConverter">
			<a>fecha</a>
			<b>fecha</b>
		</field>
	</mapping>
		<mapping>
  		<class-a>org.gestoresmadrid.core.general.model.vo.EnvioDataVO</class-a>
  		<class-b>org.gestoresmadrid.oegam2comun.envioData.view.dto.EnvioDataDto</class-b>
  		<field>
  			<a>id.proceso</a>
  			<b>proceso</b>
  		</field>
  		<field>
  			<a>id.cola</a>
  			<b>cola</b>
  		</field>
  		<field>
  			<a>id.correcta</a>
  			<b>correcta</b>
  		</field>
  	</mapping>
  	<mapping>
  		<class-a>org.gestoresmadrid.core.evolucionSemaforo.model.vo.EvolucionSemaforoVO</class-a>
  		<class-b>org.gestoresmadrid.oegamComun.semaforo.view.dto.EvolucionSemaforoDto</class-b>
  		<field>
  			<a>fecha</a>
  			<b>fecha</b>
  		</field>
  	</mapping>
</mappings>
